pytket/extensions/pennylane/__init__.py
pytket/extensions/pennylane/_metadata.py
pytket/extensions/pennylane/pennylane_convert.py
pytket/extensions/pennylane/pytket_device.py
pytket_pennylane-0.21.0.dist-info/licenses/LICENSE
tests/run_pennylane_tests.py
tests/test_backends.py
tests/test_conversion.py
pytket_pennylane-0.21.0.dist-info/METADATA
pytket_pennylane-0.21.0.dist-info/WHEEL
pytket_pennylane-0.21.0.dist-info/entry_points.txt
pytket_pennylane-0.21.0.dist-info/top_level.txt
pytket_pennylane-0.21.0.dist-info/RECORD
