Metadata-Version: 2.4
Name: pytket-pennylane
Version: 0.21.0
Summary: Pytket extension and Pennylane plugin.
Author-email: TKET development team <tket-support@quantinuum.com>
Maintainer-email: TKET development team <tket-support@quantinuum.com>
License:                                  Apache License
Project-URL: documentation, https://tket.quantinuum.com/extensions/pytket-pennylane/index.html
Project-URL: source, https://github.com/Quantinuum/pytket-pennylane
Project-URL: tracker, https://github.com/Quantinuum/pytket-pennylane/issues
Classifier: Environment :: Console
Classifier: Programming Language :: Python :: 3.11
Classifier: Programming Language :: Python :: 3.12
Classifier: Programming Language :: Python :: 3.13
Classifier: Operating System :: MacOS :: MacOS X
Classifier: Operating System :: POSIX :: Linux
Classifier: Operating System :: Microsoft :: Windows
Classifier: Intended Audience :: Developers
Classifier: Intended Audience :: Science/Research
Classifier: Topic :: Scientific/Engineering
Requires-Python: <4.0,>=3.11
License-File: LICENSE
Requires-Dist: pytket>=2.11.0
Requires-Dist: pennylane>=0.43.1
Requires-Dist: pytket-qiskit>=0.75.0
Dynamic: license-file
